<Weave encoding="dynamic">
  <WeaveProperties name="WeaveProperties">
    <axisFontBold>true</axisFontBold>
    <axisFontColor>0</axisFontColor>
    <axisFontFamily>Sophia Nubian</axisFontFamily>
    <axisFontItalic>false</axisFontItalic>
    <axisFontSize>14</axisFontSize>
    <axisFontUnderline>false</axisFontUnderline>
    <backgroundColor>13421772</backgroundColor>
    <cssStyleSheetName>weaveStyle.css</cssStyleSheetName>
    <dashboardMode>false</dashboardMode>
    <dashedSelectionBox>5,5</dashedSelectionBox>
    <dataInfoURL/>
    <debugScreenBounds>false</debugScreenBounds>
    <enableAboutMenu>true</enableAboutMenu>
    <enableAdd2DHistogram>true</enableAdd2DHistogram>
    <enableAddBarChart>true</enableAddBarChart>
    <enableAddColorLegend>true</enableAddColorLegend>
    <enableAddColormapHistogram>true</enableAddColormapHistogram>
    <enableAddDataFilter>true</enableAddDataFilter>
    <enableAddDataSource>true</enableAddDataSource>
    <enableAddDataTable>true</enableAddDataTable>
    <enableAddDimensionSliderTool>true</enableAddDimensionSliderTool>
    <enableAddGaugeTool>true</enableAddGaugeTool>
    <enableAddGrailsDataSource>true</enableAddGrailsDataSource>
    <enableAddHistogram>true</enableAddHistogram>
    <enableAddLineChart>true</enableAddLineChart>
    <enableAddMap>true</enableAddMap>
    <enableAddPieChart>true</enableAddPieChart>
    <enableAddPieChartHistogram>true</enableAddPieChartHistogram>
    <enableAddRScriptEditor>true</enableAddRScriptEditor>
    <enableAddScatterplot>true</enableAddScatterplot>
    <enableAddThermometerTool>true</enableAddThermometerTool>
    <enableAddTimeSliderTool>true</enableAddTimeSliderTool>
    <enableAddWeaveDataSource>true</enableAddWeaveDataSource>
    <enableCascadeAllWindows>true</enableCascadeAllWindows>
    <enableClearCurrentSelection>true</enableClearCurrentSelection>
    <enableCloseAllWindows>true</enableCloseAllWindows>
    <enableCreateSubsets>true</enableCreateSubsets>
    <enableDataMenu>true</enableDataMenu>
    <enableDebugAlert>false</enableDebugAlert>
    <enableDynamicTools>true</enableDynamicTools>
    <enableEditDataSource>true</enableEditDataSource>
    <enableExportApplicationScreenshot>true</enableExportApplicationScreenshot>
    <enableExportDataTable>true</enableExportDataTable>
    <enableExportToolImage>true</enableExportToolImage>
    <enableFullscreen>true</enableFullscreen>
    <enableGeometryProbing>false</enableGeometryProbing>
    <enableGoFullscreen>true</enableGoFullscreen>
    <enableManageSavedSelections>true</enableManageSavedSelections>
    <enableManageSavedSubsets>true</enableManageSavedSubsets>
    <enableMenuBar>true</enableMenuBar>
    <enableMinimizeAllWindows>true</enableMinimizeAllWindows>
    <enableMouseWheel>true</enableMouseWheel>
    <enableNewDataset>true</enableNewDataset>
    <enableNewUserWizard>true</enableNewUserWizard>
    <enablePanelCoordsPercentageMode>true</enablePanelCoordsPercentageMode>
    <enableProbeAnimation>true</enableProbeAnimation>
    <enableProbeLines>true</enableProbeLines>
    <enableRefreshHierarchies>true</enableRefreshHierarchies>
    <enableRemoveSubsets>true</enableRemoveSubsets>
    <enableRestoreAllMinimizedWindows>true</enableRestoreAllMinimizedWindows>
    <enableRightClick>true</enableRightClick>
    <enableSaveCurrentSelection>true</enableSaveCurrentSelection>
    <enableSaveCurrentSubset>true</enableSaveCurrentSubset>
    <enableSearchForRecord>true</enableSearchForRecord>
    <enableSelectionsMenu>true</enableSelectionsMenu>
    <enableSessionBookmarks>true</enableSessionBookmarks>
    <enableSessionEdit>false</enableSessionEdit>
    <enableSessionExport>true</enableSessionExport>
    <enableSessionImport>true</enableSessionImport>
    <enableSessionMenu>false</enableSessionMenu>
    <enableShowAllRecords>true</enableShowAllRecords>
    <enableSubsetControls>true</enableSubsetControls>
    <enableSubsetsMenu>true</enableSubsetsMenu>
    <enableTaskbar>true</enableTaskbar>
    <enableTileAllWindows>true</enableTileAllWindows>
    <enableToolAttributeEditing>true</enableToolAttributeEditing>
    <enableToolProbe>true</enableToolProbe>
    <enableToolSelection>true</enableToolSelection>
    <enableUserPreferences>true</enableUserPreferences>
    <enableWindowMenu>true</enableWindowMenu>
    <pageTitle>Open Indicators Weave</pageTitle>
    <panelTitleFontBold>false</panelTitleFontBold>
    <panelTitleFontColor>16777215</panelTitleFontColor>
    <panelTitleFontFamily/>
    <panelTitleFontItalic>false</panelTitleFontItalic>
    <panelTitleFontSize>12</panelTitleFontSize>
    <panelTitleFontUnderline>false</panelTitleFontUnderline>
    <probeInnerGlowAlpha>0.9</probeInnerGlowAlpha>
    <probeInnerGlowBlur>5</probeInnerGlowBlur>
    <probeInnerGlowColor>16777215</probeInnerGlowColor>
    <probeInnerGlowStrength>10</probeInnerGlowStrength>
    <probeOuterGlowAlpha>1</probeOuterGlowAlpha>
    <probeOuterGlowBlur>3</probeOuterGlowBlur>
    <probeOuterGlowColor>0</probeOuterGlowColor>
    <probeOuterGlowStrength>3</probeOuterGlowStrength>
    <probeToolTipBackgroundAlpha>0.9</probeToolTipBackgroundAlpha>
    <probeToolTipBackgroundColor>15725756</probeToolTipBackgroundColor>
    <probeToolTipFontColor>0</probeToolTipFontColor>
    <rServiceURL>/WeaveServices/RService</rServiceURL>
    <searchServiceURLs>Wikipedia|http://en.wikipedia.org/wiki/Special:Search?search=
Google|http://www.google.com/search?q=
Google Images|http://images.google.com/images?q=
Google Maps|http://maps.google.com/maps?t=h&amp;q=</searchServiceURLs>
    <selectionAlphaAmount>0.5</selectionAlphaAmount>
    <selectionBlurringAmount>4</selectionBlurringAmount>
    <sessionStateEditor>TextArea</sessionStateEditor>
    <shadowAlpha>0.5</shadowAlpha>
    <shadowAngle>45</shadowAngle>
    <shadowBlur>4</shadowBlur>
    <shadowColor>0</shadowColor>
    <shadowDistance>2</shadowDistance>
    <showAttributeSelector>true</showAttributeSelector>
    <showColorController>true</showColorController>
    <showCopyright>true</showCopyright>
    <showEquationEditor>true</showEquationEditor>
    <showKeyTypeInColumnTitle>false</showKeyTypeInColumnTitle>
    <showProbeToolTipEditor>true</showProbeToolTipEditor>
    <showVisToolCloseDialog>false</showVisToolCloseDialog>
    <version>1.0 Beta 1</version>
    <windowSnapGridSize>4</windowSnapGridSize>
  </WeaveProperties>
  <ColorColumn name="defaultColorColumn">
    <internalDynamicColumn encoding="dynamic">
      <GlobalObjectReference name="defaultColorBinColumn"/>
    </internalDynamicColumn>
    <ramp encoding="xml">
      <colorRamp name="Jet" source="OIC" reverse="false" dataFormat="qualitative" category="visualization">
        <node color="0x000086" position="0"/>
        <node color="0x0000ff" position="0.1518324607329843"/>
        <node color="0x00ffff" position="0.3717277486910995"/>
        <node color="0xffff00" position="0.6282722513089005"/>
        <node color="0xff0000" position="0.8952879581151832"/>
        <node color="0x860000" position="1"/>
      </colorRamp>
    </ramp>
  </ColorColumn>
  <BinnedColumn name="defaultColorBinColumn">
    <binningDefinition encoding="dynamic">
      <SimpleBinningDefinition>
        <numberOfBins>10</numberOfBins>
      </SimpleBinningDefinition>
    </binningDefinition>
    <internalDynamicColumn encoding="dynamic">
      <GlobalObjectReference name="defaultColorDataColumn"/>
    </internalDynamicColumn>
  </BinnedColumn>
  <FilteredColumn name="defaultColorDataColumn">
    <filter encoding="dynamic">
      <GlobalObjectReference name="defaultSubsetKeyFilter"/>
    </filter>
    <internalDynamicColumn encoding="dynamic">
      <ReferencedColumn>
        <dynamicColumnReference encoding="dynamic">
          <HierarchyColumnReference>
            <dataSourceName>WeaveDataSource</dataSourceName>
            <hierarchyPath encoding="xml">
              <hierarchy>
                <category name="DataTables">
                  <category name="Obesity Years">
                    <attribute id="46151" min="0" keyType="US State FIPS Code" name="Percent Obese (BMI >= 30)" dataTable="Obesity Years" year="2007" max="40"/>
                  </category>
                </category>
              </hierarchy>
            </hierarchyPath>
          </HierarchyColumnReference>
        </dynamicColumnReference>
      </ReferencedColumn>
    </internalDynamicColumn>
  </FilteredColumn>
  <KeyFilter name="defaultSubsetKeyFilter">
    <excluded/>
    <included/>
    <includeMissingKeys>true</includeMissingKeys>
    <includeMissingKeyTypes>true</includeMissingKeyTypes>
  </KeyFilter>
  <KeySet name="defaultSelectionKeySet"/>
  <KeySet name="defaultProbeKeySet"/>
  <LinkableHashMap name="savedSelections" encoding="dynamic"/>
  <LinkableHashMap name="savedSubsets" encoding="dynamic"/>
  <LinkableHashMap name="Probe Header Columns" encoding="dynamic">
    <ReferencedColumn name="ReferencedColumn2">
      <dynamicColumnReference encoding="dynamic">
        <HierarchyColumnReference>
          <dataSourceName>WeaveDataSource</dataSourceName>
          <hierarchyPath encoding="xml">
            <hierarchy>
              <category name="DataTables">
                <category name="World Name Table">
                  <attribute name="Country Name" id="55268" dataTable="World Name Table" keyType="ISO ALPHA-3 Country Code"/>
                </category>
              </category>
            </hierarchy>
          </hierarchyPath>
        </HierarchyColumnReference>
      </dynamicColumnReference>
    </ReferencedColumn>
    <ReferencedColumn name="ReferencedColumn3">
      <dynamicColumnReference encoding="dynamic">
        <HierarchyColumnReference>
          <dataSourceName>WeaveDataSource</dataSourceName>
          <hierarchyPath encoding="xml">
            <hierarchy>
              <category name="DataTables">
                <category name="Obesity Years">
                  <attribute name="State" id="46150" dataTable="Obesity Years" keyType="US State FIPS Code"/>
                </category>
              </category>
            </hierarchy>
          </hierarchyPath>
        </HierarchyColumnReference>
      </dynamicColumnReference>
    </ReferencedColumn>
  </LinkableHashMap>
  <LinkableHashMap name="Probed Columns" encoding="dynamic">
    <ReferencedColumn name="ReferencedColumn2">
      <dynamicColumnReference encoding="dynamic">
        <HierarchyColumnReference>
          <dataSourceName>WeaveDataSource</dataSourceName>
          <hierarchyPath encoding="xml">
            <hierarchy>
              <category name="DataTables">
                <category name="Obesity Years">
                  <attribute id="46151" min="0" keyType="US State FIPS Code" name="Percent Obese (BMI >= 30)" dataTable="Obesity Years" year="2007" max="40"/>
                </category>
              </category>
            </hierarchy>
          </hierarchyPath>
        </HierarchyColumnReference>
      </dynamicColumnReference>
    </ReferencedColumn>
  </LinkableHashMap>
  <WeaveDataSource name="WeaveDataSource">
    <attributeHierarchy encoding="xml">
      <hierarchy name="IVPR Indicator Server">
        <category name="Obesity Years">
          <attribute name="State" id="46150" dataTable="Obesity Years" keyType="US State FIPS Code"/>
          <attribute id="46151" min="0" keyType="US State FIPS Code" name="Percent Obese (BMI >= 30)" dataTable="Obesity Years" year="1995" max="40"/>
          <attribute id="46152" min="0" keyType="US State FIPS Code" name="Percent Obese (BMI >= 30)" dataTable="Obesity Years" year="1996" max="40"/>
          <attribute id="46153" min="0" keyType="US State FIPS Code" name="Percent Obese (BMI >= 30)" dataTable="Obesity Years" year="1997" max="40"/>
          <attribute id="46154" min="0" keyType="US State FIPS Code" name="Percent Obese (BMI >= 30)" dataTable="Obesity Years" year="1998" max="40"/>
          <attribute id="46155" min="0" keyType="US State FIPS Code" name="Percent Obese (BMI >= 30)" dataTable="Obesity Years" year="1999" max="40"/>
          <attribute id="46156" min="0" keyType="US State FIPS Code" name="Percent Obese (BMI >= 30)" dataTable="Obesity Years" year="2000" max="40"/>
          <attribute id="46157" min="0" keyType="US State FIPS Code" name="Percent Obese (BMI >= 30)" dataTable="Obesity Years" year="2001" max="40"/>
          <attribute id="46158" min="0" keyType="US State FIPS Code" name="Percent Obese (BMI >= 30)" dataTable="Obesity Years" year="2002" max="40"/>
          <attribute id="46159" min="0" keyType="US State FIPS Code" name="Percent Obese (BMI >= 30)" dataTable="Obesity Years" year="2003" max="40"/>
          <attribute id="46160" min="0" keyType="US State FIPS Code" name="Percent Obese (BMI >= 30)" dataTable="Obesity Years" year="2004" max="40"/>
          <attribute id="46161" min="0" keyType="US State FIPS Code" name="Percent Obese (BMI >= 30)" dataTable="Obesity Years" year="2005" max="40"/>
          <attribute id="46162" min="0" keyType="US State FIPS Code" name="Percent Obese (BMI >= 30)" dataTable="Obesity Years" year="2006" max="40"/>
          <attribute id="46163" min="0" keyType="US State FIPS Code" name="Percent Obese (BMI >= 30)" dataTable="Obesity Years" year="2007" max="40"/>
        </category>
        <category name="State Geographies">
          <attribute name="the_geom_id" id="84989" geometryCollection="States" dataTable="States" keyType="US State FIPS Code"/>
          <attribute name="AREA" id="84990" geometryCollection="States" dataTable="States" keyType="US State FIPS Code"/>
          <attribute name="PERIMETER" id="84991" geometryCollection="States" dataTable="States" keyType="US State FIPS Code"/>
          <attribute name="ST99_D00_" id="84992" geometryCollection="States" dataTable="States" keyType="US State FIPS Code"/>
          <attribute name="ST99_D00_I" id="84993" geometryCollection="States" dataTable="States" keyType="US State FIPS Code"/>
          <attribute name="STATE" id="84994" geometryCollection="States" dataTable="States" keyType="US State FIPS Code"/>
          <attribute name="NAME" id="84995" geometryCollection="States" dataTable="States" keyType="US State FIPS Code"/>
          <attribute name="LSAD" id="84996" geometryCollection="States" dataTable="States" keyType="US State FIPS Code"/>
          <attribute name="REGION" id="84997" geometryCollection="States" dataTable="States" keyType="US State FIPS Code"/>
          <attribute name="DIVISION" id="84998" geometryCollection="States" dataTable="States" keyType="US State FIPS Code"/>
          <attribute name="LSAD_TRANS" id="84999" geometryCollection="States" dataTable="States" keyType="US State FIPS Code"/>
        </category>
        <category name="World Name Table">
          <attribute name="Population 2005" id="55265" dataTable="World Name Table" keyType="ISO ALPHA-3 Country Code"/>
          <attribute name="Area" id="55266" dataTable="World Name Table" keyType="ISO ALPHA-3 Country Code"/>
          <attribute name="Country or area name" id="55267" dataTable="World Name Table" keyType="ISO ALPHA-3 Country Code"/>
          <attribute name="Country Name" id="55268" dataTable="World Name Table" keyType="ISO ALPHA-3 Country Code"/>
          <attribute name="Alt 1 Country Name" id="55269" dataTable="World Name Table" keyType="ISO ALPHA-3 Country Code"/>
          <attribute name="Iso 2 Code Country" id="55270" dataTable="World Name Table" keyType="ISO ALPHA-3 Country Code"/>
          <attribute name="Alt 2 Country name" id="55271" dataTable="World Name Table" keyType="ISO ALPHA-3 Country Code"/>
          <attribute name="Iso 3 Code Country" id="55272" dataTable="World Name Table" keyType="ISO ALPHA-3 Country Code"/>
          <attribute name="ISO 3 Country" id="55273" dataTable="World Name Table" keyType="ISO ALPHA-3 Country Code"/>
          <attribute name="ISO ALPHA-3 code" id="55274" dataTable="World Name Table" keyType="ISO ALPHA-3 Country Code"/>
          <attribute name="Region" id="55275" dataTable="World Name Table" keyType="ISO ALPHA-3 Country Code"/>
          <attribute name="Numerical code" id="55276" dataTable="World Name Table" keyType="ISO ALPHA-3 Country Code"/>
          <attribute name="Latitude" id="55277" dataTable="World Name Table" keyType="ISO ALPHA-3 Country Code"/>
          <attribute name="Longitude" id="55278" dataTable="World Name Table" keyType="ISO ALPHA-3 Country Code"/>
        </category>
      </hierarchy>
    </attributeHierarchy>
    <hierarchyURL/>
    <url>/WeaveServices/DataService</url>
  </WeaveDataSource>
  <TimeSliderTool name="TimeSliderTool">
    <buttonRadius>3</buttonRadius>
    <children encoding="dynamic">
      <SimpleInteractiveVisualization name="visualization">
        <axesAlpha>NaN</axesAlpha>
        <axesColor>NaN</axesColor>
        <axesThickness>NaN</axesThickness>
        <axisFontBold>true</axisFontBold>
        <axisFontColor>0</axisFontColor>
        <axisFontFamily>Sophia Nubian</axisFontFamily>
        <axisFontItalic>false</axisFontItalic>
        <axisFontSize>14</axisFontSize>
        <axisFontUnderline>false</axisFontUnderline>
        <dataBounds>
          <xMax>NaN</xMax>
          <xMin>NaN</xMin>
          <yMax>NaN</yMax>
          <yMin>NaN</yMin>
        </dataBounds>
        <defaultMouseMode>InteractiveVisualization.SELECT_MODE_REPLACE</defaultMouseMode>
        <enableAutoZoomToExtent>true</enableAutoZoomToExtent>
        <enableAutoZoomXToNiceNumbers>false</enableAutoZoomXToNiceNumbers>
        <enableAutoZoomYToNiceNumbers>false</enableAutoZoomYToNiceNumbers>
        <enableFixedAspectRatio>false</enableFixedAspectRatio>
        <enableZoomAndPan>true</enableZoomAndPan>
        <gridLineAlpha>NaN</gridLineAlpha>
        <gridLineColor>NaN</gridLineColor>
        <gridLineThickness>NaN</gridLineThickness>
        <includeNonSelectableLayersInAutoZoom>false</includeNonSelectableLayersInAutoZoom>
        <layers encoding="dynamic"/>
        <marginBottom>0</marginBottom>
        <marginLeft>0</marginLeft>
        <marginRight>0</marginRight>
        <marginTop>0</marginTop>
        <maxZoomLevel>16</maxZoomLevel>
        <minScreenSize>128</minScreenSize>
        <minZoomLevel>0</minZoomLevel>
        <shadowAmount>0</shadowAmount>
      </SimpleInteractiveVisualization>
    </children>
    <closeable>false</closeable>
    <currentSliderPosition>12</currentSliderPosition>
    <draggable>false</draggable>
    <enableBorders>false</enableBorders>
    <enableControlPanel>true</enableControlPanel>
    <enableHelpPanel>true</enableHelpPanel>
    <labelsLinkableString>1995,1996,1997,1998,1999,2000,2001,2002,2003,2004,2005,2006,2007</labelsLinkableString>
    <maximizable>false</maximizable>
    <maximized>false</maximized>
    <minimizable>false</minimizable>
    <minimized>false</minimized>
    <panelBackgroundColor>NaN</panelBackgroundColor>
    <panelBorderColor>NaN</panelBorderColor>
    <panelHeight>9.2004%</panelHeight>
    <panelStyleList/>
    <panelWidth>100%</panelWidth>
    <panelX>0%</panelX>
    <panelY>90.69%</panelY>
    <pinnable>true</pinnable>
    <pinnableToBack>true</pinnableToBack>
    <pinned>false</pinned>
    <pinnedToBack>false</pinnedToBack>
    <resizeable>false</resizeable>
    <showCloseDialog>false</showCloseDialog>
    <timerDelay>2500</timerDelay>
    <toolTitle/>
  </TimeSliderTool>
  <CompoundBarChartTool name="CompoundBarChartTool">
    <buttonRadius>3</buttonRadius>
    <children encoding="dynamic">
      <SimpleInteractiveVisualization name="visualization">
        <axesAlpha>1</axesAlpha>
        <axesColor>11579568</axesColor>
        <axesThickness>10</axesThickness>
        <axisFontBold>true</axisFontBold>
        <axisFontColor>0</axisFontColor>
        <axisFontFamily>Sophia Nubian</axisFontFamily>
        <axisFontItalic>false</axisFontItalic>
        <axisFontSize>14</axisFontSize>
        <axisFontUnderline>false</axisFontUnderline>
        <dataBounds>
          <xMax>48.5</xMax>
          <xMin>-0.5</xMin>
          <yMax>40</yMax>
          <yMin>0</yMin>
        </dataBounds>
        <defaultMouseMode>InteractiveVisualization.SELECT_MODE_REPLACE</defaultMouseMode>
        <enableAutoZoomToExtent>true</enableAutoZoomToExtent>
        <enableAutoZoomXToNiceNumbers>false</enableAutoZoomXToNiceNumbers>
        <enableAutoZoomYToNiceNumbers>false</enableAutoZoomYToNiceNumbers>
        <enableFixedAspectRatio>false</enableFixedAspectRatio>
        <enableZoomAndPan>false</enableZoomAndPan>
        <gridLineAlpha>1</gridLineAlpha>
        <gridLineColor>14540253</gridLineColor>
        <gridLineThickness>1</gridLineThickness>
        <includeNonSelectableLayersInAutoZoom>false</includeNonSelectableLayersInAutoZoom>
        <layers encoding="dynamic">
          <AxisLayer name="yAxis">
            <isOverlay>false</isOverlay>
            <layerIsVisible>true</layerIsVisible>
            <plotter encoding="dynamic">
              <SimpleAxisPlotter>
                <axisLabelDistance>-10</axisLabelDistance>
                <axisLabelRelativeAngle>45</axisLabelRelativeAngle>
                <axisLineDataBounds>
                  <xMax>-0.5</xMax>
                  <xMin>-0.5</xMin>
                  <yMax>40</yMax>
                  <yMin>0</yMin>
                </axisLineDataBounds>
                <axisLineMaxValue>40</axisLineMaxValue>
                <axisLineMinValue>0</axisLineMinValue>
                <forceTickCount>false</forceTickCount>
                <keySet>
                  <keyFilter encoding="dynamic"/>
                </keySet>
                <labelDistanceIsVertical>false</labelDistanceIsVertical>
                <labelHorizontalAlign>right</labelHorizontalAlign>
                <labelNumberFormatter>
                  <decimalSeparatorFrom>.</decimalSeparatorFrom>
                  <decimalSeparatorTo>.</decimalSeparatorTo>
                  <precision>0</precision>
                  <rounding>none</rounding>
                  <thousandsSeparatorFrom>,</thousandsSeparatorFrom>
                  <thousandsSeparatorTo>,</thousandsSeparatorTo>
                  <useNegativeSign>true</useNegativeSign>
                  <useThousandsSeparator>true</useThousandsSeparator>
                </labelNumberFormatter>
                <labelTextAlignment>left</labelTextAlignment>
                <labelVerticalAlign>bottom</labelVerticalAlign>
                <overrideAxisName/>
                <showAxisName>true</showAxisName>
                <tickCountRequested>5</tickCountRequested>
                <tickMaxValue>NaN</tickMaxValue>
                <tickMinValue>NaN</tickMinValue>
              </SimpleAxisPlotter>
            </plotter>
            <selectionFilter encoding="dynamic"/>
          </AxisLayer>
          <AxisLayer name="xAxis">
            <isOverlay>false</isOverlay>
            <layerIsVisible>true</layerIsVisible>
            <plotter encoding="dynamic">
              <SimpleAxisPlotter>
                <axisLabelDistance>-10</axisLabelDistance>
                <axisLabelRelativeAngle>-45</axisLabelRelativeAngle>
                <axisLineDataBounds>
                  <xMax>48.5</xMax>
                  <xMin>-0.5</xMin>
                  <yMax>0</yMax>
                  <yMin>0</yMin>
                </axisLineDataBounds>
                <axisLineMaxValue>48.5</axisLineMaxValue>
                <axisLineMinValue>-0.5</axisLineMinValue>
                <forceTickCount>true</forceTickCount>
                <keySet>
                  <keyFilter encoding="dynamic"/>
                </keySet>
                <labelDistanceIsVertical>false</labelDistanceIsVertical>
                <labelHorizontalAlign>right</labelHorizontalAlign>
                <labelNumberFormatter>
                  <decimalSeparatorFrom>.</decimalSeparatorFrom>
                  <decimalSeparatorTo>.</decimalSeparatorTo>
                  <precision>0</precision>
                  <rounding>none</rounding>
                  <thousandsSeparatorFrom>,</thousandsSeparatorFrom>
                  <thousandsSeparatorTo>,</thousandsSeparatorTo>
                  <useNegativeSign>true</useNegativeSign>
                  <useThousandsSeparator>true</useThousandsSeparator>
                </labelNumberFormatter>
                <labelTextAlignment>left</labelTextAlignment>
                <labelVerticalAlign>top</labelVerticalAlign>
                <overrideAxisName/>
                <showAxisName>true</showAxisName>
                <tickCountRequested>49</tickCountRequested>
                <tickMaxValue>48</tickMaxValue>
                <tickMinValue>0</tickMinValue>
              </SimpleAxisPlotter>
            </plotter>
            <selectionFilter encoding="dynamic"/>
          </AxisLayer>
          <SelectablePlotLayer name="plot">
            <backgroundIsVisible>true</backgroundIsVisible>
            <enableBitmapFilters>true</enableBitmapFilters>
            <layerIsSelectable>true</layerIsSelectable>
            <layerIsVisible>true</layerIsVisible>
            <plotter encoding="dynamic">
              <CompoundBarChartPlotter>
                <barSpacing>0</barSpacing>
                <chartColors encoding="xml">
                  <colorRamp name="Doppler Radar" source="OIC" dataFormat="qualitative" category="aesthetic">
                    <node color="0x04E9E7" position="0"/>
                    <node color="0x009DF4" position="0.08"/>
                    <node color="0x0201F4" position="0.16"/>
                    <node color="0x01FC01" position="0.24"/>
                    <node color="0x00C400" position="0.32"/>
                    <node color="0x008C00" position="0.4"/>
                    <node color="0x0FDF801" position="0.48"/>
                    <node color="0xF99200" position="0.56"/>
                    <node color="0xFD0000" position="0.64"/>
                    <node color="0xBC0000" position="0.72"/>
                    <node color="0xBC0000" position="0.8"/>
                    <node color="0xF800FD" position="0.88"/>
                    <node color="0x9854C6" position="1.0"/>
                  </colorRamp>
                </chartColors>
                <colorColumn>
                  <defaultValue>NaN</defaultValue>
                  <internalDynamicColumn encoding="dynamic">
                    <GlobalObjectReference name="defaultColorColumn"/>
                  </internalDynamicColumn>
                </colorColumn>
                <groupMode>false</groupMode>
                <heightColumns encoding="dynamic">
                  <ReferencedColumn name="ReferencedColumn2">
                    <dynamicColumnReference encoding="dynamic">
                      <HierarchyColumnReference>
                        <dataSourceName>WeaveDataSource</dataSourceName>
                        <hierarchyPath encoding="xml">
                          <hierarchy>
                            <category name="DataTables">
                              <category name="Obesity Years">
                                <attribute id="46163" min="0" keyType="US State FIPS Code" name="Percent Obese (BMI >= 30)" dataTable="Obesity Years" year="2007" max="40"/>
                              </category>
                            </category>
                          </hierarchy>
                        </hierarchyPath>
                      </HierarchyColumnReference>
                    </dynamicColumnReference>
                  </ReferencedColumn>
                </heightColumns>
                <horizontalMode>false</horizontalMode>
                <keySet>
                  <keyFilter encoding="dynamic">
                    <GlobalObjectReference name="defaultSubsetKeyFilter"/>
                  </keyFilter>
                </keySet>
                <lineStyle encoding="dynamic">
                  <SolidLineStyle>
                    <alpha>
                      <defaultValue>0.5</defaultValue>
                      <internalDynamicColumn encoding="dynamic"/>
                    </alpha>
                    <caps>
                      <defaultValue/>
                      <internalDynamicColumn encoding="dynamic"/>
                    </caps>
                    <color>
                      <defaultValue>0</defaultValue>
                      <internalDynamicColumn encoding="dynamic"/>
                    </color>
                    <enabled>
                      <defaultValue>true</defaultValue>
                      <internalDynamicColumn encoding="dynamic"/>
                    </enabled>
                    <joints>
                      <defaultValue/>
                      <internalDynamicColumn encoding="dynamic"/>
                    </joints>
                    <miterLimit>
                      <defaultValue>3</defaultValue>
                      <internalDynamicColumn encoding="dynamic"/>
                    </miterLimit>
                    <pixelHinting>
                      <defaultValue>false</defaultValue>
                      <internalDynamicColumn encoding="dynamic"/>
                    </pixelHinting>
                    <scaleMode>
                      <defaultValue>normal</defaultValue>
                      <internalDynamicColumn encoding="dynamic"/>
                    </scaleMode>
                    <weight>
                      <defaultValue>1</defaultValue>
                      <internalDynamicColumn encoding="dynamic"/>
                    </weight>
                  </SolidLineStyle>
                </lineStyle>
                <sortColumn encoding="dynamic">
                  <ReferencedColumn>
                    <dynamicColumnReference encoding="dynamic">
                      <HierarchyColumnReference>
                        <dataSourceName>WeaveDataSource</dataSourceName>
                        <hierarchyPath encoding="xml">
                          <hierarchy>
                            <category name="DataTables">
                              <category name="Obesity Years">
                                <attribute id="46151" min="0" keyType="US State FIPS Code" name="Percent Obese (BMI >= 30)" dataTable="Obesity Years" year="2007" max="40"/>
                              </category>
                            </category>
                          </hierarchy>
                        </hierarchyPath>
                      </HierarchyColumnReference>
                    </dynamicColumnReference>
                  </ReferencedColumn>
                </sortColumn>
                <zoomToSubset>false</zoomToSubset>
              </CompoundBarChartPlotter>
            </plotter>
            <probeFilter encoding="dynamic">
              <GlobalObjectReference name="defaultProbeKeySet"/>
            </probeFilter>
            <selectionFilter encoding="dynamic">
              <GlobalObjectReference name="defaultSelectionKeySet"/>
            </selectionFilter>
            <subsetFilter encoding="dynamic">
              <GlobalObjectReference name="defaultSubsetKeyFilter"/>
            </subsetFilter>
            <useTextBitmapFilters>false</useTextBitmapFilters>
          </SelectablePlotLayer>
          <PlotLayer name="probeLine">
            <isOverlay>false</isOverlay>
            <layerIsVisible>true</layerIsVisible>
            <plotter encoding="dynamic">
              <ProbeLinePlotter>
                <keySet>
                  <keyFilter encoding="dynamic"/>
                </keySet>
                <lineStyle encoding="dynamic">
                  <SolidLineStyle>
                    <alpha>
                      <defaultValue>0.5</defaultValue>
                      <internalDynamicColumn encoding="dynamic"/>
                    </alpha>
                    <caps>
                      <defaultValue/>
                      <internalDynamicColumn encoding="dynamic"/>
                    </caps>
                    <color>
                      <defaultValue>0</defaultValue>
                      <internalDynamicColumn encoding="dynamic"/>
                    </color>
                    <enabled>
                      <defaultValue>true</defaultValue>
                      <internalDynamicColumn encoding="dynamic"/>
                    </enabled>
                    <joints>
                      <defaultValue/>
                      <internalDynamicColumn encoding="dynamic"/>
                    </joints>
                    <miterLimit>
                      <defaultValue>3</defaultValue>
                      <internalDynamicColumn encoding="dynamic"/>
                    </miterLimit>
                    <pixelHinting>
                      <defaultValue>false</defaultValue>
                      <internalDynamicColumn encoding="dynamic"/>
                    </pixelHinting>
                    <scaleMode>
                      <defaultValue>normal</defaultValue>
                      <internalDynamicColumn encoding="dynamic"/>
                    </scaleMode>
                    <weight>
                      <defaultValue>1</defaultValue>
                      <internalDynamicColumn encoding="dynamic"/>
                    </weight>
                  </SolidLineStyle>
                </lineStyle>
              </ProbeLinePlotter>
            </plotter>
            <selectionFilter encoding="dynamic"/>
          </PlotLayer>
        </layers>
        <marginBottom>95</marginBottom>
        <marginLeft>80</marginLeft>
        <marginRight>20</marginRight>
        <marginTop>10</marginTop>
        <maxZoomLevel>16</maxZoomLevel>
        <minScreenSize>128</minScreenSize>
        <minZoomLevel>0</minZoomLevel>
        <shadowAmount>0</shadowAmount>
      </SimpleInteractiveVisualization>
    </children>
    <closeable>true</closeable>
    <draggable>true</draggable>
    <enableBorders>true</enableBorders>
    <enableControlPanel>true</enableControlPanel>
    <enableHelpPanel>true</enableHelpPanel>
    <includeToolAttributesInProbe>false</includeToolAttributesInProbe>
    <labelColumn encoding="dynamic">
      <ReferencedColumn>
        <dynamicColumnReference encoding="dynamic">
          <HierarchyColumnReference>
            <dataSourceName>WeaveDataSource</dataSourceName>
            <hierarchyPath encoding="xml">
              <hierarchy>
                <category name="DataTables">
                  <category name="States">
                    <attribute name="NAME" id="84995" geometryCollection="States" dataTable="States" keyType="US State FIPS Code"/>
                  </category>
                </category>
              </hierarchy>
            </hierarchyPath>
          </HierarchyColumnReference>
        </dynamicColumnReference>
      </ReferencedColumn>
    </labelColumn>
    <maximizable>true</maximizable>
    <maximized>false</maximized>
    <minimizable>true</minimizable>
    <minimized>false</minimized>
    <panelBackgroundColor>NaN</panelBackgroundColor>
    <panelBorderColor>NaN</panelBorderColor>
    <panelHeight>90.69%</panelHeight>
    <panelStyleList/>
    <panelWidth>100%</panelWidth>
    <panelX>0%</panelX>
    <panelY>0%</panelY>
    <pinnable>true</pinnable>
    <pinnableToBack>false</pinnableToBack>
    <pinned>false</pinned>
    <pinnedToBack>false</pinnedToBack>
    <resizeable>true</resizeable>
    <showAllLabels>true</showAllLabels>
    <showCloseDialog>false</showCloseDialog>
    <sizeAxisTickCountRequested>5</sizeAxisTickCountRequested>
    <toolTitle/>
  </CompoundBarChartTool>
  <ColorBinLegendTool name="ColorBinLegendTool">
    <buttonRadius>3</buttonRadius>
    <children encoding="dynamic">
      <SimpleInteractiveVisualization name="visualization">
        <axesAlpha>NaN</axesAlpha>
        <axesColor>NaN</axesColor>
        <axesThickness>NaN</axesThickness>
        <axisFontBold>true</axisFontBold>
        <axisFontColor>0</axisFontColor>
        <axisFontFamily>Sophia Nubian</axisFontFamily>
        <axisFontItalic>false</axisFontItalic>
        <axisFontSize>14</axisFontSize>
        <axisFontUnderline>false</axisFontUnderline>
        <dataBounds>
          <xMax>1</xMax>
          <xMin>0</xMin>
          <yMax>9.5</yMax>
          <yMin>-0.5</yMin>
        </dataBounds>
        <defaultMouseMode>InteractiveVisualization.SELECT_MODE_REPLACE</defaultMouseMode>
        <enableAutoZoomToExtent>true</enableAutoZoomToExtent>
        <enableAutoZoomXToNiceNumbers>false</enableAutoZoomXToNiceNumbers>
        <enableAutoZoomYToNiceNumbers>false</enableAutoZoomYToNiceNumbers>
        <enableFixedAspectRatio>false</enableFixedAspectRatio>
        <enableZoomAndPan>false</enableZoomAndPan>
        <gridLineAlpha>NaN</gridLineAlpha>
        <gridLineColor>NaN</gridLineColor>
        <gridLineThickness>NaN</gridLineThickness>
        <includeNonSelectableLayersInAutoZoom>false</includeNonSelectableLayersInAutoZoom>
        <layers encoding="dynamic">
          <SelectablePlotLayer name="plot">
            <backgroundIsVisible>true</backgroundIsVisible>
            <enableBitmapFilters>true</enableBitmapFilters>
            <layerIsSelectable>true</layerIsSelectable>
            <layerIsVisible>true</layerIsVisible>
            <plotter encoding="dynamic">
              <ColorBinLegendPlotter>
                <dynamicColorColumn encoding="dynamic">
                  <GlobalObjectReference name="defaultColorColumn"/>
                </dynamicColorColumn>
                <keySet>
                  <keyFilter encoding="dynamic">
                    <GlobalObjectReference name="defaultSubsetKeyFilter"/>
                  </keyFilter>
                </keySet>
                <lineStyle>
                  <alpha>
                    <defaultValue>0.5</defaultValue>
                    <internalDynamicColumn encoding="dynamic"/>
                  </alpha>
                  <caps>
                    <defaultValue/>
                    <internalDynamicColumn encoding="dynamic"/>
                  </caps>
                  <color>
                    <defaultValue>0</defaultValue>
                    <internalDynamicColumn encoding="dynamic"/>
                  </color>
                  <enabled>
                    <defaultValue>true</defaultValue>
                    <internalDynamicColumn encoding="dynamic"/>
                  </enabled>
                  <joints>
                    <defaultValue/>
                    <internalDynamicColumn encoding="dynamic"/>
                  </joints>
                  <miterLimit>
                    <defaultValue>3</defaultValue>
                    <internalDynamicColumn encoding="dynamic"/>
                  </miterLimit>
                  <pixelHinting>
                    <defaultValue>false</defaultValue>
                    <internalDynamicColumn encoding="dynamic"/>
                  </pixelHinting>
                  <scaleMode>
                    <defaultValue>normal</defaultValue>
                    <internalDynamicColumn encoding="dynamic"/>
                  </scaleMode>
                  <weight>
                    <defaultValue>1</defaultValue>
                    <internalDynamicColumn encoding="dynamic"/>
                  </weight>
                </lineStyle>
                <shapeSize>20</shapeSize>
              </ColorBinLegendPlotter>
            </plotter>
            <probeFilter encoding="dynamic">
              <GlobalObjectReference name="defaultProbeKeySet"/>
            </probeFilter>
            <selectionFilter encoding="dynamic">
              <GlobalObjectReference name="defaultSelectionKeySet"/>
            </selectionFilter>
            <subsetFilter encoding="dynamic">
              <GlobalObjectReference name="defaultSubsetKeyFilter"/>
            </subsetFilter>
            <useTextBitmapFilters>true</useTextBitmapFilters>
          </SelectablePlotLayer>
        </layers>
        <marginBottom>5</marginBottom>
        <marginLeft>5</marginLeft>
        <marginRight>5</marginRight>
        <marginTop>25</marginTop>
        <maxZoomLevel>16</maxZoomLevel>
        <minScreenSize>128</minScreenSize>
        <minZoomLevel>0</minZoomLevel>
        <shadowAmount>0</shadowAmount>
      </SimpleInteractiveVisualization>
    </children>
    <closeable>true</closeable>
    <draggable>true</draggable>
    <enableBorders>false</enableBorders>
    <enableControlPanel>true</enableControlPanel>
    <enableHelpPanel>true</enableHelpPanel>
    <maximizable>false</maximizable>
    <maximized>false</maximized>
    <minimizable>false</minimizable>
    <minimized>false</minimized>
    <panelBackgroundColor>NaN</panelBackgroundColor>
    <panelBorderColor>NaN</panelBorderColor>
    <panelHeight>29.354%</panelHeight>
    <panelStyleList/>
    <panelWidth>15%</panelWidth>
    <panelX>6.5625%</panelX>
    <panelY>3.5049%</panelY>
    <pinnable>true</pinnable>
    <pinnableToBack>false</pinnableToBack>
    <pinned>true</pinned>
    <pinnedToBack>false</pinnedToBack>
    <resizeable>false</resizeable>
    <showCloseDialog>false</showCloseDialog>
    <toolTitle/>
  </ColorBinLegendTool>
</Weave>